appstream_python/Collection.py
appstream_python/Component.py
appstream_python/Release.py
appstream_python/Shared.py
appstream_python/StandardConstants.py
appstream_python/__init__.py
appstream_python/_helper.py
appstream_python/version.txt
appstream_python-0.8.1.dist-info/LICENSE
appstream_python-0.8.1.dist-info/METADATA
appstream_python-0.8.1.dist-info/WHEEL
appstream_python-0.8.1.dist-info/top_level.txt
appstream_python-0.8.1.dist-info/RECORD
